Topsis/102017186.py
Topsis/__init__.py
Topsis_ParvGupta_102017186-1.0.0.dist-info/LICENSE.txt
Topsis_ParvGupta_102017186-1.0.0.dist-info/METADATA
Topsis_ParvGupta_102017186-1.0.0.dist-info/WHEEL
Topsis_ParvGupta_102017186-1.0.0.dist-info/top_level.txt
Topsis_ParvGupta_102017186-1.0.0.dist-info/RECORD
