Metadata-Version: 2.1
Name: Topsis-ParvGupta-102017186
Version: 1.0.0
Summary: A command line python program to implement the Topsis
Author: Parv Gupta
Author-email: pgupta4_be20@thapar.edu
License: MIT
Keywords: Topsis,Multiple Criteria
Classifier: Development Status :: 3 - Alpha
Classifier: Intended Audience :: Developers
Classifier: Topic :: Software Development :: Build Tools
Classifier: License :: OSI Approved :: MIT License
Classifier: Programming Language :: Python :: 3
Classifier: Programming Language :: Python :: 3.4
Classifier: Programming Language :: Python :: 3.5
Classifier: Programming Language :: Python :: 3.6
License-File: LICENSE.txt
Requires-Dist: pandas
Requires-Dist: numpy
Requires-Dist: sys
